riskpy/__init__.py
riskpy/automl/__init__.py
riskpy/automl/pipeline.py
riskpy/common/__init__.py
riskpy/common/misc.py
riskpy/graphs/__init__.py
riskpy/graphs/graphs.py
riskpy/hdfs/__init__.py
riskpy/hdfs/hdfs.py
riskpy/modeling/__init__.py
riskpy/modeling/binning.py
riskpy/modeling/modeler.py
riskpy/modeling/scoring.py
riskpy/modeling/data_prepocessing/__init__.py
riskpy/modeling/data_prepocessing/lag_generator.py
riskpy/modeling/data_prepocessing/time_series.py
riskpy/utilities/__init__.py
riskpy/utilities/common_metrics.py
riskpy/utilities/specific_metrics.py
riskpy-0.0.4.2.dist-info/LICENSE.txt
riskpy-0.0.4.2.dist-info/METADATA
riskpy-0.0.4.2.dist-info/WHEEL
riskpy-0.0.4.2.dist-info/top_level.txt
riskpy-0.0.4.2.dist-info/RECORD
