Metadata-Version: 2.1
Name: riskpy
Version: 0.0.4.2
Summary: Risk-manager's pack
Home-page: http://google.com
Author: Igor Shcherbakov
Author-email: pimanov.d@gmail.com
License: MIT
Keywords: modeling,risks,statistics
Platform: UNKNOWN
License-File: LICENSE.txt
Requires-Dist: numpy (==1.18.5)
Requires-Dist: pandas (==0.25.3)
Requires-Dist: scikit-learn (==0.21.3)
Requires-Dist: matplotlib (==2.0.2)
Requires-Dist: statsmodels (==0.11.1)
Requires-Dist: seaborn (==0.7.1)
Requires-Dist: scipy (==1.4.1)
